QuadratiK/__init__.py
QuadratiK/datasets/__init__.py
QuadratiK/datasets/_dataset.py
QuadratiK/datasets/data/__init__.py
QuadratiK/datasets/data/wifi_localization.txt
QuadratiK/datasets/data/wine.txt
QuadratiK/datasets/data/wine_dataset.rst
QuadratiK/datasets/data/wireless_localization_dataset.rst
QuadratiK/datasets/data/wisconsin_breast_cancer.txt
QuadratiK/datasets/data/wisconsin_breast_cancer_dataset.rst
QuadratiK/kernel_test/__init__.py
QuadratiK/kernel_test/_cv_functions.py
QuadratiK/kernel_test/_h_selection.py
QuadratiK/kernel_test/_kernel_test.py
QuadratiK/kernel_test/_utils.py
QuadratiK/poisson_kernel_test/__init__.py
QuadratiK/poisson_kernel_test/_cv_functions.py
QuadratiK/poisson_kernel_test/_poisson_kernel_test.py
QuadratiK/poisson_kernel_test/_utils.py
QuadratiK/spherical_clustering/__init__.py
QuadratiK/spherical_clustering/_pkbc.py
QuadratiK/spherical_clustering/_pkbd.py
QuadratiK/spherical_clustering/_utils.py
QuadratiK/tools/__init__.py
QuadratiK/tools/_utils.py
QuadratiK/tools/graphics.py
QuadratiK/tools/tools.py
QuadratiK/ui/.streamlit/config.toml
QuadratiK/ui/_Introduction.py
QuadratiK/ui/__init__.py
QuadratiK/ui/_dashboard.py
QuadratiK/ui/pages/1_Normality_Test.py
QuadratiK/ui/pages/2_Two_Sample_Test.py
QuadratiK/ui/pages/3_K_Sample_Test.py
QuadratiK/ui/pages/4_Tuning_Parameter_h_Selection.py
QuadratiK/ui/pages/5_Uniformity_Test.py
QuadratiK/ui/pages/6_Data_generation_from_PKBD_Models.py
QuadratiK/ui/pages/7_Clustering_on_Sphere.py
QuadratiK/ui/pages/assets/hselect_format.png
QuadratiK/ui/pages/assets/ksample_test_format.png
QuadratiK/ui/pages/assets/normality_test_format.png
QuadratiK/ui/pages/assets/pkbd.png
QuadratiK/ui/pages/assets/two_sample_test_format.png
QuadratiK/ui/pages/assets/uniformity_test_format.png
docs/Makefile
docs/make.bat
docs/requirements.txt
docs/source/_static/css/custom.css
docs/source/_static/images/ub_logo.png
docs/source/_templates/autosummary/class.rst
docs/source/_templates/autosummary/function.rst
quadratik-1.1.3.dist-info/LICENSE
quadratik-1.1.3.dist-info/METADATA
quadratik-1.1.3.dist-info/WHEEL
quadratik-1.1.3.dist-info/RECORD
