Metadata-Version: 2.3
Name: QuadratiK
Version: 1.1.3
Summary: QuadratiK includes test for multivariate normality, test for uniformity on the Sphere, non-parametric two- and k-sample tests, random generation of points from the Poisson kernel-based density and clustering algorithm for spherical data.
License: GPL-3.0-only
Author: Giovanni Saraceno, Marianthi Markatou, Raktim Mukhopadhyay, Mojgan Golzy
Author-email: gsaracen@buffalo.edu, markatou@buffalo.edu, raktimmu@buffalo.edu, golzym@health.missouri.edu
Maintainer: Raktim Mukhopadhyay
Maintainer-email: raktimmu@buffalo.edu
Requires-Python: >=3.9, !=2.7.*, !=3.0.*, !=3.1.*, !=3.2.*, !=3.3.*, !=3.4.*, !=3.5.*, !=3.6.*, !=3.7.*, !=3.8.*
Classifier: License :: OSI Approved :: GNU General Public License v3 (GPLv3)
Classifier: Programming Language :: Python :: 3
Classifier: Programming Language :: Python :: 3.9
Classifier: Programming Language :: Python :: 3.10
Classifier: Programming Language :: Python :: 3.11
Classifier: Programming Language :: Python :: 3.12
Classifier: Programming Language :: Python :: 3.13
Requires-Dist: matplotlib (>=3.8.2,<4.0.0)
Requires-Dist: numpy (>=1.26.2,<2.0.0) ; python_version >= "3.9" and python_version < "3.13"
Requires-Dist: numpy (>=2.0.0,<3.0.0) ; python_version >= "3.13"
Requires-Dist: pandas (>=2.1.3,<3.0.0)
Requires-Dist: plotly (>=5.15.0,<6.0.0)
Requires-Dist: scikit-learn (>=1.3,<2.0)
Requires-Dist: scipy (>=1.11,<2.0)
Requires-Dist: streamlit (>=1.30.0,<2.0.0)
Requires-Dist: tabulate (>=0.8,<0.9)
Project-URL: Documentation, https://quadratik.readthedocs.io
Project-URL: Homepage, https://github.com/rmj3197/QuadratiK
